flask_apollo/__init__.py
flask_apollo/_apollo_app.py
flask_apollo/apollo.py
flask_apollo-0.2.24011623.dist-info/METADATA
flask_apollo-0.2.24011623.dist-info/WHEEL
flask_apollo-0.2.24011623.dist-info/top_level.txt
flask_apollo-0.2.24011623.dist-info/RECORD
