Metadata-Version: 2.1
Name: flask-apollo
Version: 0.2.24011623
Summary: Flask Apollo Apply
Home-page: https://github.com/BingerYang/Flask-Apollo
Author: binger
Author-email: <xuehen_521@126.com>
Maintainer: binger
Maintainer-email: <xuehen_521@126.com>
Platform: all
Requires-Python: >=3.4
